dicmer/__init__.py
tests/__init__.py
tests/test_all.py
dicmer-0.1.dist-info/LICENSE.md
dicmer-0.1.dist-info/METADATA
dicmer-0.1.dist-info/WHEEL
dicmer-0.1.dist-info/top_level.txt
dicmer-0.1.dist-info/RECORD
