Metadata-Version: 2.1
Name: dicmer
Version: 0.1
Summary: Mini library for recursively merging dictionaries
Home-page: https://github.com/ashep/dicmer
Author: Oleksandr Shepetko
Author-email: a@shepetko.com
License: UNKNOWN
Download-URL: https://github.com/ashep/dicmer/archive/master.zip
Platform: UNKNOWN
Classifier: Development Status :: 5 - Production/Stable
Classifier: Intended Audience :: Developers
Classifier: License :: OSI Approved :: MIT License
Classifier: Operating System :: OS Independent
Classifier: Programming Language :: Python :: 3.5
Classifier: Programming Language :: Python :: 3.6
Classifier: Programming Language :: Python :: 3.7
Classifier: Programming Language :: Python :: 3.8
Classifier: Topic :: Software Development :: Libraries :: Python Modules
